PyTrinamicMicro/PyTrinamicMicro.py
PyTrinamicMicro/TMCL_Bridge.py
PyTrinamicMicro/TMCL_Slave.py
PyTrinamicMicro/__init__.py
PyTrinamicMicro/tmcl_analyzer.py
PyTrinamicMicro/tmcl_bootloader.py
PyTrinamicMicro/version.py
PyTrinamicMicro/platforms/motionpy/examples/firmware_update/fw_update_can.py
PyTrinamicMicro/platforms/motionpy/examples/io/blinky.py
PyTrinamicMicro/platforms/motionpy/examples/io/buttons_leds.py
PyTrinamicMicro/platforms/motionpy/examples/linear_distance/linear_distance_bounds.py
PyTrinamicMicro/platforms/motionpy/examples/linear_distance/linear_distance_velocity.py
PyTrinamicMicro/platforms/motionpy/examples/modules/TMCM1161/TMCM1161_RS232_rotate.py
PyTrinamicMicro/platforms/motionpy/examples/modules/TMCM1161/TMCM1161_RS485_rotate.py
PyTrinamicMicro/platforms/motionpy/examples/modules/TMCM1240/TMCM1240_CAN_rotate.py
PyTrinamicMicro/platforms/motionpy/examples/modules/TMCM1240/TMCM1240_RS485_rotate.py
PyTrinamicMicro/platforms/motionpy/examples/modules/TMCM1270/TMCM1270_rotate.py
PyTrinamicMicro/platforms/motionpy/examples/modules/hc_sr04_multi/hc_sr04_multi_log.py
PyTrinamicMicro/platforms/motionpy/examples/modules/max/max14001pmb.py
PyTrinamicMicro/platforms/motionpy/examples/tmcl_analyzer/can_logger.py
PyTrinamicMicro/platforms/motionpy/examples/tmcl_bridge/tmcl_bridge_uart_can.py
PyTrinamicMicro/platforms/motionpy/examples/tmcl_bridge/tmcl_bridge_uart_rs232.py
PyTrinamicMicro/platforms/motionpy/examples/tmcl_bridge/tmcl_bridge_uart_rs485.py
PyTrinamicMicro/platforms/motionpy/examples/tmcl_bridge/tmcl_bridge_uart_x.py
PyTrinamicMicro/platforms/motionpy/examples/tmcl_bridge/tmcl_bridge_usb_can.py
PyTrinamicMicro/platforms/motionpy/examples/tmcl_bridge/tmcl_bridge_usb_rs232.py
PyTrinamicMicro/platforms/motionpy/examples/tmcl_bridge/tmcl_bridge_usb_rs485.py
PyTrinamicMicro/platforms/motionpy/examples/tmcl_bridge/tmcl_bridge_usb_uart.py
PyTrinamicMicro/platforms/motionpy/examples/tmcl_bridge/tmcl_bridge_usb_x.py
PyTrinamicMicro-0.0.2.dist-info/LICENSE
PyTrinamicMicro-0.0.2.dist-info/METADATA
PyTrinamicMicro-0.0.2.dist-info/WHEEL
PyTrinamicMicro-0.0.2.dist-info/top_level.txt
PyTrinamicMicro-0.0.2.dist-info/RECORD
